art_adk/__init__.py
art_adk/async_adk.py
art_adk/auth.py
art_adk/constant.py
art_adk/cryptobox.py
art_adk/exceptions.py
art_adk/http_poll.py
art_adk/interception.py
art_adk/socket.py
art_adk/sse_client.py
art_adk/subscription.py
art_adk/sync_adk.py
art_adk/sync_wrapper.py
art_adk/utils/__init__.py
art_adk/utils/event_emitter.py
art_adk/utils/server_data_utils.py
art_adk-0.0.1.dist-info/WHEEL
art_adk-0.0.1.dist-info/METADATA
art_adk-0.0.1.dist-info/RECORD
