Metadata-Version: 2.3
Name: art_adk
Version: 0.0.1
Summary: Python SDK for ART WebSocket platform with sync/async support
Keywords: websocket,realtime,art,adk,messaging,pubsub
Author: Aiotrix Private Limited
License: MIT
Classifier: Development Status :: 4 - Beta
Classifier: Intended Audience :: Developers
Classifier: License :: OSI Approved :: MIT License
Classifier: Programming Language :: Python :: 3
Classifier: Programming Language :: Python :: 3.8
Classifier: Programming Language :: Python :: 3.9
Classifier: Programming Language :: Python :: 3.10
Classifier: Programming Language :: Python :: 3.11
Classifier: Programming Language :: Python :: 3.12
Classifier: Topic :: Software Development :: Libraries :: Python Modules
Classifier: Topic :: Communications
Requires-Dist: aiohttp>=3.8.0
Requires-Dist: websockets>=10.0,<15.0
Requires-Dist: pynacl>=1.5.0
Requires-Python: >=3.8
Project-URL: Homepage, https://arealtimetech.com
